GCS_xml_csv_transformer/__init__.py
GCS_xml_csv_transformer/main.py
GCS_xml_csv_transformer-0.0.dist-info/METADATA
GCS_xml_csv_transformer-0.0.dist-info/WHEEL
GCS_xml_csv_transformer-0.0.dist-info/entry_points.txt
GCS_xml_csv_transformer-0.0.dist-info/top_level.txt
GCS_xml_csv_transformer-0.0.dist-info/RECORD
