Metadata-Version: 2.1
Name: GCS-xml-csv-transformer
Version: 0.0
Requires-Dist: google-cloud-storage
